setup.cfg
setup.py
rpc_thrift.egg-info/PKG-INFO
rpc_thrift.egg-info/SOURCES.txt
rpc_thrift.egg-info/dependency_links.txt
rpc_thrift.egg-info/top_level.txt
src/TMultiplexedProcessor.py
src/TSCons.py
src/TSerialization.py
src/TTornado.py
src/Thrift.py
src/__init__.py
src/protocol/TBase.py
src/protocol/TBinaryProtocol.py
src/protocol/TCompactProtocol.py
src/protocol/TJSONProtocol.py
src/protocol/TMultiplexedProtocol.py
src/protocol/TProtocol.py
src/protocol/TProtocolDecorator.py
src/protocol/__init__.py
src/protocol/fastbinary.c
src/server/THttpServer.py
src/server/TNonblockingServer.py
src/server/TProcessPoolServer.py
src/server/TServer.py
src/server/__init__.py
src/transport/THttpClient.py
src/transport/TSocket.py
src/transport/TTransport.py
src/transport/TTwisted.py
src/transport/__init__.py